MANIFEST.in
README.md
setup.cfg
setup.py
ppadb_uiautomator.egg-info/PKG-INFO
ppadb_uiautomator.egg-info/SOURCES.txt
ppadb_uiautomator.egg-info/dependency_links.txt
ppadb_uiautomator.egg-info/requires.txt
ppadb_uiautomator.egg-info/top_level.txt
test/test_device.py
test/test_device_obj.py
test/test_jsonrpc.py
test/test_misc.py
test/test_param_to_property.py
test/test_selector.py
test/test_server.py
uiautomator/__init__.py
uiautomator/automation.py
uiautomator/selector.py
uiautomator/libs/app-uiautomator-test.apk
uiautomator/libs/app-uiautomator.apk
uiautomator/libs/bundle.jar
uiautomator/libs/uiautomator-stub.jar
uiautomator/rpc/__init__.py
uiautomator/rpc/json_rpc.py